{"legislative_session": "114", "identifier": "HB 1453", "title": "Portland - Subject to local approval, deletes provisions requiring a referendum to sell, lease, or otherwise dispose of the city's water or light plant. - Amends Chapter 568 of the Private Acts of 1939; as amended.", "from_organization": "~{\"classification\": \"lower\"}", "classification": ["bill"], "subject": ["Portland"], "abstracts": [], "other_titles": [], "other_identifiers": [{"identifier": "SB 1482"}], "actions": [{"description": "Filed for introduction", "date": "2025-12-03", "organization_id": "~{\"classification\": \"lower\"}", "classification": ["filing"], "related_entities": []}, {"description": "Intro., P1C.", "date": "2026-01-13", "organization_id": "~{\"classification\": \"lower\"}", "classification": ["introduction"], "related_entities": []}, {"description": "P2C, ref. to Private Acts Committee - State & Local Government Committee", "date": "2026-01-14", "organization_id": "~{\"classification\": \"lower\"}", "classification": ["referral-committee"], "related_entities": []}, {"description": "Placed on cal. Private Acts Committee for 1/26/2026", "date": "2026-01-21", "organization_id": "~{\"classification\": \"lower\"}", "classification": [], "related_entities": []}, {"description": "Meeting Canceled", "date": "2026-01-22", "organization_id": "~{\"classification\": \"lower\"}", "classification": [], "related_entities": []}], "sponsorships": [{"name": "Lamberth", "classification": "primary", "entity_type": "person", "primary": true, "person_id": "~{\"name\": \"Lamberth\"}", "organization_id": null}], "related_bills": [{"identifier": "SB 1482", "legislative_session": "114", "relation_type": "companion"}], "versions": [{"note": "Current Version", "links": [{"url": "https://www.capitol.tn.gov/Bills/114/Bill/HB1453.pdf", "media_type": "application/pdf"}], "date": "", "classification": ""}], "documents": [], "citations": [], "sources": [{"url": "https://wapp.capitol.tn.gov/apps/BillInfo/Default?BillNumber=HB1453&ga=114", "note": ""}], "extras": {}, "jurisdiction": {"id": "ocd-jurisdiction/country:us/state:tn/government", "name": "Tennessee", "classification": "state", "division_id": "ocd-division/country:us/state:tn"}, "scraped_at": "2026-02-12T08:36:04+00:00", "_id": "deadb31e-07ed-11f1-9e04-964bb929dc07"}