{"legislative_session": "114", "identifier": "SB 1843", "title": "Drugs, Synthetic or Analogue - As introduced, enacts the \"Nitrous Oxide Abuse Prevention and Retail Sale Prohibition Act.\" - Amends TCA Title 39; Title 57, Chapter 7; Title 63 and Title 67, Chapter 4, Part 10.", "from_organization": "~{\"classification\": \"upper\"}", "classification": ["bill"], "subject": ["Drugs", "Synthetic or Analogue"], "abstracts": [], "other_titles": [], "other_identifiers": [{"identifier": "HB 1644"}], "actions": [{"description": "Filed for introduction", "date": "2026-01-21", "organization_id": "~{\"classification\": \"upper\"}", "classification": ["filing"], "related_entities": []}, {"description": "Introduced, Passed on First Consideration", "date": "2026-01-22", "organization_id": "~{\"classification\": \"upper\"}", "classification": ["introduction"], "related_entities": []}], "sponsorships": [{"name": "Briggs", "classification": "primary", "entity_type": "person", "primary": true, "person_id": "~{\"name\": \"Briggs\"}", "organization_id": null}], "related_bills": [{"identifier": "HB 1644", "legislative_session": "114", "relation_type": "companion"}], "versions": [{"note": "Current Version", "links": [{"url": "https://www.capitol.tn.gov/Bills/114/Bill/SB1843.pdf", "media_type": "application/pdf"}], "date": "", "classification": ""}], "documents": [{"note": "Fiscal Note", "links": [{"url": "http://www.capitol.tn.gov/Bills/114/Fiscal/HB1644.pdf", "media_type": ""}], "date": "", "classification": ""}], "citations": [], "sources": [{"url": "https://wapp.capitol.tn.gov/apps/BillInfo/Default?BillNumber=SB1843&ga=114", "note": ""}], "extras": {}, "jurisdiction": {"id": "ocd-jurisdiction/country:us/state:tn/government", "name": "Tennessee", "classification": "state", "division_id": "ocd-division/country:us/state:tn"}, "scraped_at": "2026-02-11T08:37:10+00:00", "_id": "db98879a-0724-11f1-8079-16dd925c1911"}