{"legislative_session": "114", "identifier": "SJR 0620", "title": "Constitutional Amendments - Proposes an amendment to Article I of the Constitution of Tennessee to prohibit the state from compelling a person to undergo medical treatment, even in the case of a declared state emergency.  -", "from_organization": "~{\"classification\": \"upper\"}", "classification": ["joint resolution"], "subject": ["Constitutional Amendments"], "abstracts": [], "other_titles": [], "other_identifiers": [], "actions": [{"description": "Filed for introduction", "date": "2026-01-22", "organization_id": "~{\"classification\": \"upper\"}", "classification": ["filing"], "related_entities": []}], "sponsorships": [{"name": "Hensley", "classification": "primary", "entity_type": "person", "primary": true, "person_id": "~{\"name\": \"Hensley\"}", "organization_id": null}], "related_bills": [], "versions": [{"note": "Current Version", "links": [{"url": "https://www.capitol.tn.gov/Bills/114/Bill/SJR0620.pdf", "media_type": "application/pdf"}], "date": "", "classification": ""}], "documents": [{"note": "Fiscal Note", "links": [{"url": "http://www.capitol.tn.gov/Bills/114/Fiscal/SJR0620.pdf", "media_type": ""}], "date": "", "classification": ""}], "citations": [], "sources": [{"url": "https://wapp.capitol.tn.gov/apps/BillInfo/Default?BillNumber=SJR0620&ga=114", "note": ""}], "extras": {}, "jurisdiction": {"id": "ocd-jurisdiction/country:us/state:tn/government", "name": "Tennessee", "classification": "state", "division_id": "ocd-division/country:us/state:tn"}, "scraped_at": "2026-02-02T08:32:34+00:00", "_id": "b94e59a4-0011-11f1-bf89-16e6e595a927"}