{"legislative_session": "114", "identifier": "SB 1785", "title": "Taxes, Exemption and Credits - As introduced, establishes a sales tax holiday on food and food ingredients and on prepared food from July 1, 2026, through September 30, 2026, if purchased by a person at least 65 years of age. - Amends TCA Section 67-6-228 and Title 67, Chapter 6, Part 3.", "from_organization": "~{\"classification\": \"upper\"}", "classification": ["bill"], "subject": ["Exemption and Credits", "Taxes"], "abstracts": [], "other_titles": [], "other_identifiers": [{"identifier": "HB 1486"}], "actions": [{"description": "Filed for introduction", "date": "2026-01-20", "organization_id": "~{\"classification\": \"upper\"}", "classification": ["filing"], "related_entities": []}, {"description": "Introduced, Passed on First Consideration", "date": "2026-01-21", "organization_id": "~{\"classification\": \"upper\"}", "classification": ["introduction"], "related_entities": []}], "sponsorships": [{"name": "Reeves", "classification": "primary", "entity_type": "person", "primary": true, "person_id": "~{\"name\": \"Reeves\"}", "organization_id": null}], "related_bills": [{"identifier": "HB 1486", "legislative_session": "114", "relation_type": "companion"}], "versions": [{"note": "Current Version", "links": [{"url": "https://www.capitol.tn.gov/Bills/114/Bill/SB1785.pdf", "media_type": "application/pdf"}], "date": "", "classification": ""}], "documents": [{"note": "Fiscal Note", "links": [{"url": "http://www.capitol.tn.gov/Bills/114/Fiscal/HB1486.pdf", "media_type": ""}], "date": "", "classification": ""}], "citations": [], "sources": [{"url": "https://wapp.capitol.tn.gov/apps/BillInfo/Default?BillNumber=SB1785&ga=114", "note": ""}], "extras": {}, "jurisdiction": {"id": "ocd-jurisdiction/country:us/state:tn/government", "name": "Tennessee", "classification": "state", "division_id": "ocd-division/country:us/state:tn"}, "scraped_at": "2026-02-04T08:29:54+00:00", "_id": "ae67c942-01a3-11f1-b846-12b57ebc7b6f"}