{"legislative_session": "114", "identifier": "SB 1813", "title": "Public Funds and Financing - As introduced, enacts the \"Tennessee Transactional Gold and Silver Act,\" which recognizes gold and silver as legal tender for private transactions and, when accepted, for paying state and local taxes or fees; authorizes the creation of a secure bullion depository and an electronic payment system to support the use of gold and silver; exempts gold and silver transactions from state and local taxation. - Amends TCA Title 9, Chapter 4.", "from_organization": "~{\"classification\": \"upper\"}", "classification": ["bill"], "subject": ["Public Funds and Financing"], "abstracts": [], "other_titles": [], "other_identifiers": [], "actions": [{"description": "Filed for introduction", "date": "2026-01-20", "organization_id": "~{\"classification\": \"upper\"}", "classification": ["filing"], "related_entities": []}, {"description": "Introduced, Passed on First Consideration", "date": "2026-01-21", "organization_id": "~{\"classification\": \"upper\"}", "classification": ["introduction"], "related_entities": []}], "sponsorships": [{"name": "Bailey", "classification": "primary", "entity_type": "person", "primary": true, "person_id": "~{\"name\": \"Bailey\"}", "organization_id": null}], "related_bills": [], "versions": [{"note": "Current Version", "links": [{"url": "https://www.capitol.tn.gov/Bills/114/Bill/SB1813.pdf", "media_type": "application/pdf"}], "date": "", "classification": ""}], "documents": [], "citations": [], "sources": [{"url": "https://wapp.capitol.tn.gov/apps/BillInfo/Default?BillNumber=SB1813&ga=114", "note": ""}], "extras": {}, "jurisdiction": {"id": "ocd-jurisdiction/country:us/state:tn/government", "name": "Tennessee", "classification": "state", "division_id": "ocd-division/country:us/state:tn"}, "scraped_at": "2026-02-05T08:31:55+00:00", "_id": "20fb2e1c-026d-11f1-b2d7-46fed30d6071"}