{"legislative_session": "114", "identifier": "HB 1799", "title": "Comptroller, State - As introduced, deletes the reports the comptroller is required to submit to the general assembly regarding the provision of broadband services in historically unserved areas and the Tennessee Helping Heroes Scholarship Program; revises the information the comptroller is required to submit to the general assembly regarding the property tax relief program. - Amends TCA Section 7-59-316; Section 49-4-938 and Section 67-5-701.", "from_organization": "~{\"classification\": \"lower\"}", "classification": ["bill"], "subject": ["Comptroller", "State"], "abstracts": [], "other_titles": [], "other_identifiers": [{"identifier": "SB 1687"}], "actions": [{"description": "Filed for introduction", "date": "2026-01-21", "organization_id": "~{\"classification\": \"lower\"}", "classification": ["filing"], "related_entities": []}, {"description": "Intro., P1C.", "date": "2026-01-22", "organization_id": "~{\"classification\": \"lower\"}", "classification": ["introduction"], "related_entities": []}], "sponsorships": [], "related_bills": [{"identifier": "SB 1687", "legislative_session": "114", "relation_type": "companion"}], "versions": [{"note": "Current Version", "links": [{"url": "https://www.capitol.tn.gov/Bills/114/Bill/HB1799.pdf", "media_type": "application/pdf"}], "date": "", "classification": ""}], "documents": [{"note": "Fiscal Note", "links": [{"url": "http://www.capitol.tn.gov/Bills/114/Fiscal/SB1687.pdf", "media_type": ""}], "date": "", "classification": ""}], "citations": [], "sources": [{"url": "https://wapp.capitol.tn.gov/apps/BillInfo/Default?BillNumber=HB1799&ga=114", "note": ""}], "extras": {}, "jurisdiction": {"id": "ocd-jurisdiction/country:us/state:tn/government", "name": "Tennessee", "classification": "state", "division_id": "ocd-division/country:us/state:tn"}, "scraped_at": "2026-02-08T08:22:25+00:00", "_id": "4c783c54-04c7-11f1-8cec-c67d9da5ccf6"}