{"legislative_session": "114", "identifier": "SB 1917", "title": "Teachers, Principals and School Personnel - As introduced, creates a pathway for a person to obtain an alternative instructional leader license for purposes of serving as a principal, an assistant principal, or an instructional supervisor. - Amends TCA Title 49, Chapter 5.", "from_organization": "~{\"classification\": \"upper\"}", "classification": ["bill"], "subject": ["Principals and School Personnel", "Teachers"], "abstracts": [], "other_titles": [], "other_identifiers": [{"identifier": "HB 1117"}], "actions": [{"description": "Filed for introduction", "date": "2026-01-21", "organization_id": "~{\"classification\": \"upper\"}", "classification": ["filing"], "related_entities": []}, {"description": "Introduced, Passed on First Consideration", "date": "2026-01-22", "organization_id": "~{\"classification\": \"upper\"}", "classification": ["introduction"], "related_entities": []}], "sponsorships": [{"name": "Seal", "classification": "primary", "entity_type": "person", "primary": true, "person_id": "~{\"name\": \"Seal\"}", "organization_id": null}], "related_bills": [{"identifier": "HB 1117", "legislative_session": "114", "relation_type": "companion"}], "versions": [{"note": "Current Version", "links": [{"url": "https://www.capitol.tn.gov/Bills/114/Bill/SB1917.pdf", "media_type": "application/pdf"}], "date": "", "classification": ""}], "documents": [{"note": "Fiscal Note", "links": [{"url": "http://www.capitol.tn.gov/Bills/114/Fiscal/HB1117.pdf", "media_type": ""}], "date": "", "classification": ""}], "citations": [], "sources": [{"url": "https://wapp.capitol.tn.gov/apps/BillInfo/Default?BillNumber=SB1917&ga=114", "note": ""}], "extras": {}, "jurisdiction": {"id": "ocd-jurisdiction/country:us/state:tn/government", "name": "Tennessee", "classification": "state", "division_id": "ocd-division/country:us/state:tn"}, "scraped_at": "2026-02-07T08:20:08+00:00", "_id": "d09489cc-03fd-11f1-b470-228ac767c502"}