{"legislative_session": "114", "identifier": "SB 2002", "title": "Taxes, Real Property - As introduced, limits the setting of the tax rate on property by a county, municipality, metropolitan government, or other taxing entity in any fiscal year at a rate that would render in total receipts from all levies an amount more than the receipts from that source from the immediately preceding fiscal year for the county, municipality, metropolitan government, or other taxing jurisdiction, plus an additional 2 percent, subject to certain exceptions; establishes a procedure by which the 2 percent increase may be exceeded by passage of a referendum. - Amends TCA Title 67, Chapter 5.", "from_organization": "~{\"classification\": \"upper\"}", "classification": ["bill"], "subject": ["Real Property", "Taxes"], "abstracts": [], "other_titles": [], "other_identifiers": [], "actions": [{"description": "Filed for introduction", "date": "2026-01-22", "organization_id": "~{\"classification\": \"upper\"}", "classification": ["filing"], "related_entities": []}], "sponsorships": [{"name": "Hensley", "classification": "primary", "entity_type": "person", "primary": true, "person_id": "~{\"name\": \"Hensley\"}", "organization_id": null}], "related_bills": [], "versions": [{"note": "Current Version", "links": [{"url": "https://www.capitol.tn.gov/Bills/114/Bill/SB2002.pdf", "media_type": "application/pdf"}], "date": "", "classification": ""}], "documents": [], "citations": [], "sources": [{"url": "https://wapp.capitol.tn.gov/apps/BillInfo/Default?BillNumber=SB2002&ga=114", "note": ""}], "extras": {}, "jurisdiction": {"id": "ocd-jurisdiction/country:us/state:tn/government", "name": "Tennessee", "classification": "state", "division_id": "ocd-division/country:us/state:tn"}, "scraped_at": "2026-02-10T08:40:12+00:00", "_id": "1d8c0880-065c-11f1-9b9f-36a709bbcce8"}