{"legislative_session": "114", "identifier": "SB 1478", "title": "Highways, Roads and Bridges - As introduced, adds the state representatives and state senators who represent the county where an actual or imminent transportation system failure or other emergency is located to the list of recipients of the written notice required to be provided by the commissioner of transportation in the event the commissioner enters into a contract to remedy such failure or emergency. - Amends TCA Title 54.", "from_organization": "~{\"classification\": \"upper\"}", "classification": ["bill"], "subject": ["Highways", "Roads and Bridges"], "abstracts": [], "other_titles": [], "other_identifiers": [], "actions": [{"description": "Filed for introduction", "date": "2025-11-17", "organization_id": "~{\"classification\": \"upper\"}", "classification": ["filing"], "related_entities": []}], "sponsorships": [{"name": "Massey", "classification": "primary", "entity_type": "person", "primary": true, "person_id": "~{\"name\": \"Massey\"}", "organization_id": null}], "related_bills": [], "versions": [{"note": "Current Version", "links": [{"url": "https://www.capitol.tn.gov/Bills/114/Bill/SB1478.pdf", "media_type": "application/pdf"}], "date": "", "classification": ""}], "documents": [], "citations": [], "sources": [{"url": "http://wapp.capitol.tn.gov/apps/BillInfo/default.aspx?BillNumber=SB1478&GA=114", "note": ""}], "extras": {}, "jurisdiction": {"id": "ocd-jurisdiction/country:us/state:tn/government", "name": "Tennessee", "classification": "state", "division_id": "ocd-division/country:us/state:tn"}, "scraped_at": "2025-12-29T08:20:14+00:00", "_id": "338c012e-e48f-11f0-92ef-b65244c29c83"}