{"identifier": "", "motion_text": "HOUSE FINANCE, WAYS, AND MEANS SUBCOMMITTEE: Rec. for pass by s/c ref. to Finance, Ways, and Means Committee  4/8/2026  Passed (3)", "motion_classification": ["passage"], "start_date": "2026-04-08", "result": "pass", "organization": "~{\"classification\": \"lower\"}", "legislative_session": "114", "bill": "346603d4-8731-11f1-90e6-6af98f0093c3", "bill_action": null, "bill_identifier": "HB 1176", "votes": [{"option": "not voting", "voter_name": "Reeves", "voter_id": "~{\"name\": \"Reeves\"}", "note": ""}], "counts": [{"option": "yes", "value": 10}, {"option": "no", "value": 2}, {"option": "not voting", "value": 1}], "sources": [{"url": "https://wapp.capitol.tn.gov/apps/BillInfo/Default?BillNumber=HB1176&ga=114", "note": ""}], "extras": {}, "_id": "34672b88-8731-11f1-90e6-6af98f0093c3"}