{"identifier": "", "motion_text": "FLOOR VOTE: REGULAR CALENDAR    PASSAGE ON THIRD CONSIDERATION  4/21/2025  Passed (1)", "motion_classification": ["passage"], "start_date": "2025-04-21", "result": "pass", "organization": "~{\"classification\": \"lower\"}", "legislative_session": "114", "bill": "73dc9bf8-851b-11f1-b2f7-aa85843a572c", "bill_action": null, "bill_identifier": "SB 0586", "votes": [{"option": "not voting", "voter_name": "Bulso", "voter_id": "~{\"name\": \"Bulso\"}", "note": ""}, {"option": "not voting", "voter_name": "Reeves", "voter_id": "~{\"name\": \"Reeves\"}", "note": ""}], "counts": [{"option": "yes", "value": 91}, {"option": "no", "value": 0}, {"option": "not voting", "value": 2}], "sources": [{"url": "https://wapp.capitol.tn.gov/apps/BillInfo/Default?BillNumber=SB0586&ga=114", "note": ""}], "extras": {}, "_id": "73dd1fec-851b-11f1-b2f7-aa85843a572c"}